pyramid_crow/__init__.py
pyramid_crow/processors.py
pyramid_crow/tests.py
pyramid_crow-0.4.2.dist-info/DESCRIPTION.rst
pyramid_crow-0.4.2.dist-info/METADATA
pyramid_crow-0.4.2.dist-info/RECORD
pyramid_crow-0.4.2.dist-info/WHEEL
pyramid_crow-0.4.2.dist-info/metadata.json
pyramid_crow-0.4.2.dist-info/top_level.txt
pyramid_crow-0.4.2.dist-info/zip-safe
