Metadata-Version: 2.0
Name: pyramid-crow
Version: 0.4.2
Summary: http context compliant automatic raven integration for pyramid
Home-page: https://github.com/npilon/pyramid_crow
Author: Nicholas Pilon
Author-email: npilon@gmail.com
License: Apache 2.0
Platform: UNKNOWN
Requires-Dist: pyramid (>=1.2dev)
Requires-Dist: raven (>=5.20.0)
